pydrobert/__init__.py
pydrobert/gpyopt/__init__.py
pydrobert_gpyopt-0.0.0.dist-info/LICENSE.txt
pydrobert_gpyopt-0.0.0.dist-info/METADATA
pydrobert_gpyopt-0.0.0.dist-info/RECORD
pydrobert_gpyopt-0.0.0.dist-info/WHEEL
pydrobert_gpyopt-0.0.0.dist-info/top_level.txt
