Metadata-Version: 2.1
Name: pydrobert-gpyopt
Version: 0.0.0
Summary: Utilities to streamline GPyOpt interfaces for ML
Home-page: https://github.com/sdrobert/pydrobert-gpyopt
Author: Sean Robertson
Author-email: sdrobert@cs.toronto.edu
License: Apache 2.0
Platform: UNKNOWN
Classifier: Development Status :: 3 - Alpha
Classifier: License :: OSI Approved :: Apache Software License
Classifier: Programming Language :: Python :: 2
Classifier: Programming Language :: Python :: 2.7
Classifier: Programming Language :: Python :: 3
Classifier: Programming Language :: Python :: 3.4
Classifier: Programming Language :: Python :: 3.5
Classifier: Programming Language :: Python :: 3.6
Classifier: Programming Language :: Python :: 3.7
Requires-Dist: numpy
Requires-Dist: future
Requires-Dist: GPyOpt
Requires-Dist: param
Requires-Dist: matplotlib
